mojo/_entrypoints.py
mojo/_package_root.py
mojo/importer.py
mojo/notebook.py
mojo/paths.py
mojo/run.py
mojo_compiler-0.26.1.0.dist-info/WHEEL
mojo_compiler-0.26.1.0.dist-info/METADATA
mojo_compiler-0.26.1.0.dist-info/entry_points.txt
mojo_compiler-0.26.1.0.data/platlib/modular/bin/lld
mojo_compiler-0.26.1.0.data/platlib/modular/bin/modular-crashpad-handler
mojo_compiler-0.26.1.0.data/platlib/modular/bin/mojo
mojo_compiler-0.26.1.0.data/platlib/modular/lib/libAsyncRTMojoBindings.so
mojo_compiler-0.26.1.0.data/platlib/modular/lib/libAsyncRTRuntimeGlobals.so
mojo_compiler-0.26.1.0.data/platlib/modular/lib/libKGENCompilerRTShared.so
mojo_compiler-0.26.1.0.data/platlib/modular/lib/libMSupportGlobals.so
mojo_compiler-0.26.1.0.data/platlib/modular/lib/libNVPTX.so
mojo_compiler-0.26.1.0.data/platlib/modular/lib/mojo/buffer.mojopkg
mojo_compiler-0.26.1.0.data/platlib/modular/lib/mojo/layout.mojopkg
mojo_compiler-0.26.1.0.data/platlib/modular/lib/mojo/std.mojopkg
mojo_compiler-0.26.1.0.dist-info/RECORD
